{
  "mobile H5 application": [
    {
      "name": "YT Music",
      "icon": "fa fa-music",
      "desc": "A music player mini-program demo imitated YouTube Music's interface, but with light mode.",
      "url": "https://github.com/went2/yt-music"
    },
    {
      "name": "On The Road",
      "icon": "fa fa-bed",
      "desc": "A Bed & Breakfast mobile web app demo built with vue3 and pinia.",
      "url": "https://github.com/went2/trip-app"
    }
  ],
  "desktop": [
    {
      "name": "Cookit",
      "icon": "fa fa-shopping-basket ",
      "desc": "A vanilla JS recipe searching application using MVC",
      "url": "https://github.com/went2/cookit"
    },
    {
      "name": "Greedy snake",
      "icon": "fa fa-circle-o-notch",
      "desc": "a greedy snake game with vanilla js and dom api",
      "url": "https://github.com/went2/greedy-snake"
    }
  ],
  "components": [
    {
      "name": "Miniprogram-navbar",
      "icon": "fa fa-bars",
      "desc": "A common navigation bar component used in Wechat miniprogram.",
      "url": "https://github.com/went2/sf-mini-navbar"
    }
  ],
  "chrome extensions": [
    {
      "name": "Leave me unlogged",
      "icon": "fa fa-universal-access",
      "desc": "A extension that automatically closes login pop-ups.",
      "url": "https://github.com/went2/leave-me-unlogged"
    }
  ]
}